tianzige/__init__.py
tianzige/__main__.py
tianzige/core.py
tianzige-0.3.0.dist-info/METADATA
tianzige-0.3.0.dist-info/WHEEL
tianzige-0.3.0.dist-info/entry_points.txt
tianzige-0.3.0.dist-info/licenses/LICENSE
tianzige-0.3.0.dist-info/RECORD
