Metadata-Version: 2.4
Name: tianzige
Version: 0.3.0
Summary: Generate Tianzige (田字格) writing grid PDFs for Chinese character practice
Project-URL: Documentation, https://github.com/username/tianzige#readme
Project-URL: Source, https://github.com/username/tianzige
Author: Hans
License-Expression: MIT
License-File: LICENSE
Keywords: chinese,grid,practice,tianzige,writing,田字格
Classifier: Development Status :: 4 - Beta
Classifier: Environment :: Console
Classifier: Intended Audience :: Education
Classifier: License :: OSI Approved :: MIT License
Classifier: Operating System :: OS Independent
Classifier: Programming Language :: Python :: 3
Classifier: Programming Language :: Python :: 3.10
Classifier: Programming Language :: Python :: 3.11
Classifier: Programming Language :: Python :: 3.12
Classifier: Topic :: Education
Classifier: Topic :: Printing
Requires-Python: >=3.10
Requires-Dist: reportlab>=4.0.0
